pytruco/__init__.py
pytruco-0.0.0.dist-info/METADATA
pytruco-0.0.0.dist-info/WHEEL
pytruco-0.0.0.dist-info/top_level.txt
pytruco-0.0.0.dist-info/RECORD
