Metadata-Version: 2.1
Name: pytruco
Version: 0.0.0
Summary: Coming soon
Author-email: JP Filevich <juanfilevich@gmail.com>
